nodemcuload.py
setup.py
nodemcuload.egg-info/PKG-INFO
nodemcuload.egg-info/SOURCES.txt
nodemcuload.egg-info/dependency_links.txt
nodemcuload.egg-info/entry_points.txt
nodemcuload.egg-info/requires.txt
nodemcuload.egg-info/top_level.txt