Metadata-Version: 1.0
Name: nodemcuload
Version: 0.0.2
Summary: NodeMCU file system utility.
Home-page: https://github.com/mossblaser/nodemcuload
Author: Jonathan Heathcote
Author-email: mail@jhnet.co.uk
License: GPLv3
Platform: UNKNOWN
